sfimpute/__init__.py
sfimpute/impute.py
sfimpute/parallel.py
sfimpute/preprocess.py
sfimpute-0.0.2.dist-info/LICENSE
sfimpute-0.0.2.dist-info/METADATA
sfimpute-0.0.2.dist-info/WHEEL
sfimpute-0.0.2.dist-info/top_level.txt
sfimpute-0.0.2.dist-info/RECORD
