Metadata-Version: 2.1
Name: sfimpute
Version: 0.0.2
Summary: An imputation method for multiplexed DNA FISH data
Author-email: Hongyu Yu <hongyuyu@unc.edu>
Project-URL: Homepage, https://github.com/hyuyu104/SnapFISH-IMPUTE
Project-URL: Bug Tracker, https://github.com/hyuyu104/SnapFISH-IMPUTE/issues
Classifier: Programming Language :: Python :: 3
Classifier: License :: OSI Approved :: MIT License
Classifier: Operating System :: OS Independent
Requires-Python: >=3.8
License-File: LICENSE
Requires-Dist: numpy >=1.19.0
Requires-Dist: pandas >=1.1.5
Requires-Dist: scipy >=1.5.4
Requires-Dist: matplotlib >=3.3.4
Requires-Dist: seaborn >=0.11.2
Requires-Dist: scikit-image >=0.21.0
Requires-Dist: scikit-learn >=1.3.0
